{
  "last_run": "run52",
  "run_id": "24624875403",
  "lean_version": "4.29.1",
  "lean_available": true,
  "total_theorems": 272,
  "proved_theorems": 266,
  "sorry_count": 12,
  "total_examples": 127,
  "lean_files": 21,
  "open_prs": [
    "PR #51 (atmosphere-run52)"
  ],
  "correspondence_coverage": "All 21 Lean files. Atmosphere.lean not yet in CORRESPONDENCE.md (next run).",
  "notes_priorities": "Next: (1) Add Atmosphere to CORRESPONDENCE.md; (2) commander_arming_fsm phase 2; (3) Update paper.tex to 272 theorems; (4) REPORT.md update",
  "notes": [
    "Rat.add_lt_add_right is Iff not function - use .mpr",
    "Rat.sub_lt_sub_right does NOT exist - use add_neg + add_lt_add_right.mpr",
    "inv_lt_inv_of_lt_rat: build manually via mul_lt_mul_right + inv_mul_cancel",
    "Rat.mul_sub does NOT exist in stdlib - use sorry or manual expansion",
    "Rat.lt_iff_sub_pos : a < b iff 0 < b - a (use .mp)",
    "neg_mono proof: Rat.neg_lt_neg + mul_lt_mul_of_pos_left",
    "negative Rat literals: -65/10000 normalizes to -13/2000 in Lean",
    "native_decide works for concrete Rat comparisons but NOT with free vars",
    "Lean 4 stdlib has NO linarith/ring/norm_num/conv - all Mathlib only",
    "simp [kConst, Rat.mul_zero, Rat.add_zero] handles T(0)=15 style goals",
    "Mathlib blocked (403 on cache proxy) - stdlib only proofs required",
    "powf/Real.rpow needs Mathlib - use sorry for transcendental functions",
    "Rat.mul_sub does not exist - needs Mathlib or manual proof by add+neg",
    "lake build runs from formal-verification/lean/",
    "barrel file: Basic.lean imports all FVSquad modules"
  ],
  "fv_targets": [
    {
      "id": "math_constrain",
      "name": "math::constrain",
      "phase": 5,
      "status": "Done",
      "lean_file": "lean/FVSquad/MathFunctions.lean"
    },
    {
      "id": "math_signNoZero",
      "name": "math::signNoZero",
      "phase": 5,
      "status": "Done - NaN bug found (issue #12)",
      "lean_file": "lean/FVSquad/MathFunctions.lean"
    },
    {
      "id": "math_countSetBits",
      "name": "math::countSetBits",
      "phase": 5,
      "status": "Done",
      "lean_file": "lean/FVSquad/MathFunctions.lean"
    },
    {
      "id": "slew_rate",
      "name": "SlewRate::update",
      "phase": 5,
      "status": "Done",
      "lean_file": "lean/FVSquad/SlewRate.lean"
    },
    {
      "id": "deadzone",
      "name": "math::deadzone",
      "phase": 5,
      "status": "Done",
      "lean_file": "lean/FVSquad/Deadzone.lean"
    },
    {
      "id": "median_filter",
      "name": "MedianFilter",
      "phase": 5,
      "status": "Done",
      "lean_file": "lean/FVSquad/MedianFilter.lean"
    },
    {
      "id": "interpolate",
      "name": "math::interpolate",
      "phase": 5,
      "status": "Done",
      "lean_file": "lean/FVSquad/Interpolate.lean"
    },
    {
      "id": "alpha_filter",
      "name": "AlphaFilter",
      "phase": 5,
      "status": "Done",
      "lean_file": "lean/FVSquad/AlphaFilter.lean"
    },
    {
      "id": "wrap_angle",
      "name": "matrix::wrap_pi",
      "phase": 3,
      "status": "6 sorry (floor needs Mathlib)",
      "lean_file": "lean/FVSquad/WrapAngle.lean"
    },
    {
      "id": "welford_mean",
      "name": "WelfordMean",
      "phase": 5,
      "status": "Done",
      "lean_file": "lean/FVSquad/WelfordMean.lean"
    },
    {
      "id": "lerp",
      "name": "math::lerp",
      "phase": 5,
      "status": "Done",
      "lean_file": "lean/FVSquad/Lerp.lean"
    },
    {
      "id": "expo",
      "name": "math::expo",
      "phase": 5,
      "status": "Done",
      "lean_file": "lean/FVSquad/Expo.lean"
    },
    {
      "id": "superexpo",
      "name": "math::superexpo",
      "phase": 5,
      "status": "Done",
      "lean_file": "lean/FVSquad/SuperExpo.lean"
    },
    {
      "id": "negate",
      "name": "math::negate",
      "phase": 5,
      "status": "Done - involution bug found (issue #21)",
      "lean_file": "lean/FVSquad/Negate.lean"
    },
    {
      "id": "ring_buffer",
      "name": "TimestampedRingBuffer",
      "phase": 5,
      "status": "Done",
      "lean_file": "lean/FVSquad/RingBuffer.lean"
    },
    {
      "id": "expo_deadzone",
      "name": "expo_deadzone",
      "phase": 5,
      "status": "Done",
      "lean_file": "lean/FVSquad/ExpoDeadzone.lean"
    },
    {
      "id": "interpolate_nxy",
      "name": "interpolateNXY N=3",
      "phase": 5,
      "status": "Done",
      "lean_file": "lean/FVSquad/InterpolateNXY.lean"
    },
    {
      "id": "interpolate_n",
      "name": "interpolateN N=2,3",
      "phase": 5,
      "status": "Done",
      "lean_file": "lean/FVSquad/InterpolateN.lean"
    },
    {
      "id": "hysteresis",
      "name": "systemlib::Hysteresis",
      "phase": 5,
      "status": "Done",
      "lean_file": "lean/FVSquad/Hysteresis.lean"
    },
    {
      "id": "sign_from_bool_sq",
      "name": "signFromBool+sq",
      "phase": 5,
      "status": "Done",
      "lean_file": "lean/FVSquad/SignFromBoolSq.lean"
    },
    {
      "id": "crc16",
      "name": "septentrio::crc16",
      "phase": 5,
      "status": "Done - 8 theorems 0 sorry",
      "lean_file": "lean/FVSquad/Crc16Fold.lean"
    },
    {
      "id": "atmosphere_density",
      "name": "atmosphere ISA model",
      "phase": 5,
      "status": "13 proved + 4 examples + 6 sorry (powf needs Mathlib)",
      "lean_file": "lean/FVSquad/Atmosphere.lean",
      "spec_file": "specs/atmosphere_informal.md"
    },
    {
      "id": "commander_arming_fsm",
      "name": "Commander arming FSM",
      "phase": 1,
      "status": "Not started",
      "lean_file": null
    }
  ]
}